flask_pancake/__init__.py
flask_pancake/commands.py
flask_pancake/constants.py
flask_pancake/extension.py
flask_pancake/flags.py
flask_pancake/registry.py
flask_pancake/utils.py
flask_pancake/views.py
flask_pancake/templates/flask_pancake/overview.html
flask_pancake-0.5.2.dist-info/LICENSE
flask_pancake-0.5.2.dist-info/METADATA
flask_pancake-0.5.2.dist-info/WHEEL
flask_pancake-0.5.2.dist-info/entry_points.txt
flask_pancake-0.5.2.dist-info/top_level.txt
flask_pancake-0.5.2.dist-info/RECORD
