Metadata-Version: 2.1
Name: flask-pancake
Version: 0.5.2
Summary: Feature Flagging for Flask
Home-page: https://github.com/MarkusH/flask-pancake
Author: Markus Holtermann
Author-email: info@markusholtermann.eu
License: MIT
Platform: UNKNOWN
Classifier: Development Status :: 4 - Beta
Classifier: Framework :: Flask
Classifier: Intended Audience :: Developers
Classifier: License :: OSI Approved :: MIT License
Classifier: Programming Language :: Python :: 3.7
Classifier: Programming Language :: Python :: 3.8
Classifier: Topic :: Software Development :: Quality Assurance
Classifier: Topic :: Software Development :: Testing
Requires-Python: >=3.7
Requires-Dist: flask (>=1.0)
Requires-Dist: flask-redis (>=0.4.0)
Requires-Dist: cached-property (<2,>=1.5)
Provides-Extra: testing
Requires-Dist: pytest (<5.4,>=5.3) ; extra == 'testing'
Requires-Dist: pytest-cov (<3,>=2.8) ; extra == 'testing'
